django_bootstrap_icons/__init__.py
django_bootstrap_icons/static/bootstrap_icons/css/bootstrap_icons.css
django_bootstrap_icons/templatetags/__init__.py
django_bootstrap_icons/templatetags/bootstrap_icons.py
django_bootstrap_icons-0.8.4.dist-info/LICENSE
django_bootstrap_icons-0.8.4.dist-info/METADATA
django_bootstrap_icons-0.8.4.dist-info/WHEEL
django_bootstrap_icons-0.8.4.dist-info/top_level.txt
django_bootstrap_icons-0.8.4.dist-info/RECORD
