Metadata-Version: 2.1
Name: django-bootstrap-icons
Version: 0.8.4
Summary: A quick way to add Bootstrap Icons with Django template tags.
Home-page: https://github.com/christianwgd/django-bootstrap-icons
Author: Christian Wiegand
License: MIT
Keywords: django,bootstrap,icons,templatetags
Classifier: Programming Language :: Python :: 3
Classifier: License :: OSI Approved :: MIT License
Classifier: Operating System :: OS Independent
Requires-Python: >=3.6
License-File: LICENSE
Requires-Dist: django
Requires-Dist: requests
